{
  "description": "## 题目描述\n\n给定链表的头结点 `head` ，请将其按 **升序** 排列并返回排序后的链表。\n\n### 示例 1\n```\n输入：head = [4,2,1,3]\n输出：[1,2,3,4]\n```\n\n### 示例 2\n```\n输入：head = [-1,5,3,4,0]\n输出：[-1,0,3,4,5]\n```\n\n### 示例 3\n```\n输入：head = []\n输出：[]\n```\n\n### 约束条件\n- 链表中节点数目在范围 `[0, 5 * 10^4]` 内\n- `-10^5 <= Node.val <= 10^5`\n\n**进阶**：能否在 `O(n log n)` 时间复杂度和常数级空间复杂度下解决此题？\n",
  "hints": [
    "提示1：思路方向 —— 回忆一下时间复杂度为 O(n log n) 的排序算法有哪些，链表数据结构适合哪种？",
    "提示2：具体方法 —— 归并排序天然适合链表，自顶向下递归拆分成小链表，再两两合并；也可尝试自底向上迭代实现常数空间",
    "提示3：实现要点 —— 合并两个有序链表时，使用 dummy 头节点简化操作；找中点时注意用快慢指针，且慢指针前需断开链表"
  ],
  "solution_outline": "使用归并排序对链表进行排序。先通过快慢指针找到链表中点，递归地对左右两部分排序，最后合并两个有序链表。自顶向下递归实现简单，自底向上迭代可实现 O(1) 空间复杂度。",
  "solution_detail": "## 解法一：自顶向下归并排序（递归）\n\n### 思路\n1. **分割**：用快慢指针找到链表中点，将链表从中点处断开，递归地对两部分分别排序\n2. **合并**：将两个已排序的子链表合并成一个有序链表\n\n### 代码\n\n```python\nclass ListNode:\n    def __init__(self, val=0, next=None):\n        self.val = val\n        self.next = next\n\ndef sortList(head: ListNode) -> ListNode:\n    if not head or not head.next:\n        return head\n    \n    # 快慢指针找中点\n    slow, fast = head, head.next\n    while fast and fast.next:\n        slow = slow.next\n        fast = fast.next.next\n    \n    # 断开链表\n    mid = slow.next\n    slow.next = None\n    \n    # 递归排序左右两部分\n    left = sortList(head)\n    right = sortList(mid)\n    \n    # 合并两个有序链表\n    return merge(left, right)\n\ndef merge(l1: ListNode, l2: ListNode) -> ListNode:\n    dummy = ListNode(0)\n    tail = dummy\n    \n    while l1 and l2:\n        if l1.val <= l2.val:\n            tail.next = l1\n            l1 = l1.next\n        else:\n            tail.next = l2\n            l2 = l2.next\n        tail = tail.next\n    \n    tail.next = l1 if l1 else l2\n    return dummy.next\n```\n\n### 复杂度分析\n- **时间复杂度**：O(n log n)，每次递归将链表对半分割，共 log n 层，每层合并需要 O(n)\n- **空间复杂度**：O(log n)，递归栈的深度\n\n---\n\n## 解法二：自底向上归并排序（迭代）\n\n### 思路\n通过控制每次合并的子链表长度（1, 2, 4, 8...），迭代地完成归并排序，避免递归栈空间。\n\n```python\ndef sortList(head: ListNode) -> ListNode:\n    if not head or not head.next:\n        return head\n    \n    # 计算链表长度\n    length = 0\n    node = head\n    while node:\n        length += 1\n        node = node.next\n    \n    dummy = ListNode(0)\n    dummy.next = head\n    step = 1\n    \n    while step < length:\n        cur = dummy.next\n        tail = dummy\n        \n        while cur:\n            # 取出两个长度为 step 的链表\n            left = cur\n            right = split(left, step)\n            cur = split(right, step)  # 下一组的起点\n            \n            # 合并并接到结果\n            merged = mergeTwoLists(left, right)\n            tail.next = merged[0]\n            tail = merged[1]\n        \n        step *= 2\n    \n    return dummy.next\n\ndef split(head: ListNode, n: int) -> ListNode:\n    \"\"\"将链表前 n 个节点切分出来，返回剩余部分的头节点\"\"\"\n    i = 1\n    while head and i < n:\n        head = head.next\n        i += 1\n    if not head:\n        return None\n    next_head = head.next\n    head.next = None\n    return next_head\n\ndef mergeTwoLists(l1: ListNode, l2: ListNode):\n    \"\"\"合并两个有序链表，返回 (头节点, 尾节点)\"\"\"\n    dummy = ListNode(0)\n    tail = dummy\n    \n    while l1 and l2:\n        if l1.val <= l2.val:\n            tail.next = l1\n            l1 = l1.next\n        else:\n            tail.next = l2\n            l2 = l2.next\n        tail = tail.next\n    \n    tail.next = l1 if l1 else l2\n    \n    # 找到尾节点\n    while tail.next:\n        tail = tail.next\n    \n    return (dummy.next, tail)\n```\n\n### 复杂度分析\n- **时间复杂度**：O(n log n)\n- **空间复杂度**：O(1)，仅使用常数个指针\n",
  "sample_code": [
    {
      "lang": "Python",
      "code": "class ListNode:\n    def __init__(self, val=0, next=None):\n        self.val = val\n        self.next = next\n\ndef sortList(head: ListNode) -> ListNode:\n    \"\"\"自顶向下归并排序\"\"\"\n    if not head or not head.next:\n        return head\n    \n    # 快慢指针找中点（关键：fast 从 head.next 开始）\n    slow, fast = head, head.next\n    while fast and fast.next:\n        slow = slow.next\n        fast = fast.next.next\n    \n    # 断开链表，分成两部分\n    mid = slow.next\n    slow.next = None\n    \n    # 递归排序\n    left = sortList(head)\n    right = sortList(mid)\n    \n    # 合并\n    return merge(left, right)\n\ndef merge(l1: ListNode, l2: ListNode) -> ListNode:\n    dummy = ListNode(0)\n    tail = dummy\n    \n    while l1 and l2:\n        if l1.val <= l2.val:\n            tail.next, l1 = l1, l1.next\n        else:\n            tail.next, l2 = l2, l2.next\n        tail = tail.next\n    \n    tail.next = l1 if l1 else l2\n    return dummy.next\n"
    }
  ],
  "common_errors": [
    "快慢指针找中点时，fast 指针初始化为 head 而非 head.next，导致中点偏左，递归时可能无限循环或栈溢出",
    "分割链表后忘记将 slow.next 设为 None，导致左右两部分仍然相连，递归无法正常分割",
    "合并两个有序链表时，未处理其中一个链表已经遍历完的情况，导致结果链表末尾缺失节点"
  ],
  "time_complexity_expected": "O(n log n)",
  "space_complexity_expected": "O(log n) 或 O(1)"
}